taxadb/__init__.py
taxadb/__main__.py
taxadb/accessionid.py
taxadb/app.py
taxadb/download.py
taxadb/names.py
taxadb/parser.py
taxadb/schema.py
taxadb/taxadb.py
taxadb/taxid.py
taxadb/util.py
taxadb/version.py
taxadb-0.12.1.dist-info/LICENSE
taxadb-0.12.1.dist-info/METADATA
taxadb-0.12.1.dist-info/WHEEL
taxadb-0.12.1.dist-info/entry_points.txt
taxadb-0.12.1.dist-info/top_level.txt
taxadb-0.12.1.dist-info/RECORD
