Metadata-Version: 2.1
Name: taxadb
Version: 0.12.1
Summary: locally query the ncbi taxonomy
Home-page: https://github.com/HadrienG/taxadb
Author: Hadrien Gourlé, Juliette Hayer, Emmanuel Quevillon
Author-email: hadrien.gourle@slu.se, juliette.hayer@slu.se,        tuco@pasteur.fr
License: MIT
Download-URL: https://github.com/HadrienG/taxadb/tarball/0.12.1
Platform: UNKNOWN
License-File: LICENSE
Requires-Dist: requests
Requires-Dist: peewee (>=3.8.2)
Requires-Dist: tqdm
Provides-Extra: mysql
Requires-Dist: PyMySQL (>=0.7.10) ; extra == 'mysql'
Provides-Extra: postgres
Requires-Dist: psycopg2 (>=2.6.2) ; extra == 'postgres'
